turbofiles/__init__.py
turbofiles/_async/__init__.py
turbofiles/_async/client.py
turbofiles/_sync/__init__.py
turbofiles/_sync/client.py
turbofiles/exceptions.py
turbofiles/py.typed
turbofiles/version.py
turbofiles-0.1.0.dist-info/METADATA
turbofiles-0.1.0.dist-info/WHEEL
turbofiles-0.1.0.dist-info/entry_points.txt
turbofiles-0.1.0.dist-info/RECORD
