Metadata-Version: 2.1
Name: turbofiles
Version: 0.1.0
Summary: TurboFiles client for Python
License: MIT
Author: junhsss
Author-email: junhsssr@gmail.com
Requires-Python: >=3.9,<4.0
Classifier: License :: OSI Approved :: MIT License
Classifier: Programming Language :: Python :: 3
Classifier: Programming Language :: Python :: 3.9
Classifier: Programming Language :: Python :: 3.10
Classifier: Programming Language :: Python :: 3.11
Classifier: Programming Language :: Python :: 3.12
Classifier: Programming Language :: Python :: 3.13
Requires-Dist: aiohttp (>=3.10.10,<4.0.0)
Requires-Dist: asyncio (>=3.4.3,<4.0.0)
